{
  "name": "write_bmp_header_dfg__7",
  "delay": {
    "MUL": 2,
    "STR": 1,
    "LSR": 1,
    "LOD": 1,
    "BNE": 1,
    "ASR": 1,
    "AND": 1,
    "ADD": 1
  },
  "resource": {
    "MUL": 1,
    "STR": 3,
    "LSR": 1,
    "LOD": 4,
    "BNE": 1,
    "ASR": 2,
    "AND": 2,
    "ADD": 4
  },
  "nodes": [
    ["MUL_3", "MUL"],
    ["ADD_4", "ADD"],
    ["ADD_8", "ADD"],
    ["LOD_9", "LOD"],
    ["ADD_13", "ADD"],
    ["LOD_14", "LOD"],
    ["MUL_17", "MUL"],
    ["ADD_18", "ADD"],
    ["ADD_36", "ADD"],
    ["STR_37", "STR"],
    ["ADD_42", "ADD"],
    ["STR_43", "STR"],
    ["AND_45", "AND"],
    ["ADD_50", "ADD"],
    ["STR_51", "STR"],
    ["ASR_53", "ASR"],
    ["AND_55", "AND"],
    ["ADD_60", "ADD"],
    ["STR_61", "STR"],
    ["ASR_63", "ASR"],
    ["AND_65", "AND"],
    ["ADD_70", "ADD"],
    ["STR_71", "STR"],
    ["ASR_73", "ASR"],
    ["AND_75", "AND"],
    ["ADD_80", "ADD"],
    ["STR_81", "STR"],
    ["AND_83", "AND"],
    ["ADD_88", "ADD"],
    ["STR_89", "STR"],
    ["ASR_91", "ASR"],
    ["AND_93", "AND"],
    ["ADD_98", "ADD"],
    ["STR_99", "STR"],
    ["ASR_101", "ASR"],
    ["AND_103", "AND"],
    ["ADD_108", "ADD"],
    ["STR_109", "STR"],
    ["ASR_111", "ASR"],
    ["AND_113", "AND"],
    ["ADD_118", "ADD"],
    ["STR_119", "STR"],
    ["ADD_124", "ADD"],
    ["STR_125", "STR"],
    ["ADD_130", "ADD"],
    ["STR_131", "STR"],
    ["ADD_133", "ADD"],
    ["LOD_134", "LOD"],
    ["AND_137", "AND"],
    ["ADD_142", "ADD"],
    ["STR_143", "STR"],
    ["ADD_145", "ADD"],
    ["LOD_146", "LOD"],
    ["LSR_150", "LSR"],
    ["AND_152", "AND"],
    ["ADD_157", "ADD"],
    ["STR_158", "STR"],
    ["ADD_160", "ADD"],
    ["LOD_161", "LOD"],
    ["LSR_165", "LSR"],
    ["AND_167", "AND"],
    ["ADD_172", "ADD"],
    ["STR_173", "STR"],
    ["ADD_175", "ADD"],
    ["LOD_176", "LOD"],
    ["LSR_180", "LSR"],
    ["AND_182", "AND"],
    ["ADD_187", "ADD"],
    ["STR_188", "STR"],
    ["ADD_190", "ADD"],
    ["LOD_191", "LOD"],
    ["AND_194", "AND"],
    ["ADD_199", "ADD"],
    ["STR_200", "STR"],
    ["ADD_202", "ADD"],
    ["LOD_203", "LOD"],
    ["LSR_207", "LSR"],
    ["AND_209", "AND"],
    ["ADD_214", "ADD"],
    ["STR_215", "STR"],
    ["ADD_217", "ADD"],
    ["LOD_218", "LOD"],
    ["LSR_222", "LSR"],
    ["AND_224", "AND"],
    ["ADD_229", "ADD"],
    ["STR_230", "STR"],
    ["ADD_232", "ADD"],
    ["LOD_233", "LOD"],
    ["LSR_237", "LSR"],
    ["AND_239", "AND"],
    ["ADD_244", "ADD"],
    ["STR_245", "STR"],
    ["ADD_250", "ADD"],
    ["STR_251", "STR"],
    ["ADD_256", "ADD"],
    ["STR_257", "STR"],
    ["AND_259", "AND"],
    ["ADD_264", "ADD"],
    ["STR_265", "STR"],
    ["ASR_267", "ASR"],
    ["AND_269", "AND"],
    ["ADD_274", "ADD"],
    ["STR_275", "STR"],
    ["ADD_277", "ADD"],
    ["LOD_278", "LOD"],
    ["BNE_282", "BNE"]
  ],
  "edges": [
    ["MUL_3", "ADD_4", "2"],
    ["ADD_4", "ADD_18", "3"],
    ["ADD_4", "AND_83", "4"],
    ["ADD_4", "ASR_91", "5"],
    ["ADD_4", "ASR_101", "6"],
    ["ADD_4", "ASR_111", "7"],
    ["ADD_8", "LOD_9", "9"],
    ["LOD_9", "MUL_17", "10"],
    ["ADD_13", "LOD_14", "12"],
    ["LOD_14", "MUL_17", "13"],
    ["MUL_17", "ADD_18", "14"],
    ["ADD_18", "AND_45", "15"],
    ["ADD_18", "ASR_53", "16"],
    ["ADD_18", "ASR_63", "17"],
    ["ADD_18", "ASR_73", "18"],
    ["ADD_36", "STR_37", "22"],
    ["ADD_42", "STR_43", "26"],
    ["AND_45", "STR_51", "28"],
    ["ADD_50", "STR_51", "31"],
    ["ASR_53", "AND_55", "33"],
    ["AND_55", "STR_61", "35"],
    ["ADD_60", "STR_61", "38"],
    ["ASR_63", "AND_65", "40"],
    ["AND_65", "STR_71", "42"],
    ["ADD_70", "STR_71", "45"],
    ["ASR_73", "AND_75", "47"],
    ["AND_75", "STR_81", "49"],
    ["ADD_80", "STR_81", "52"],
    ["AND_83", "STR_89", "54"],
    ["ADD_88", "STR_89", "57"],
    ["ASR_91", "AND_93", "59"],
    ["AND_93", "STR_99", "61"],
    ["ADD_98", "STR_99", "64"],
    ["ASR_101", "AND_103", "66"],
    ["AND_103", "STR_109", "68"],
    ["ADD_108", "STR_109", "71"],
    ["ASR_111", "AND_113", "73"],
    ["AND_113", "STR_119", "75"],
    ["ADD_118", "STR_119", "78"],
    ["ADD_124", "STR_125", "82"],
    ["ADD_130", "STR_131", "86"],
    ["ADD_133", "LOD_134", "88"],
    ["LOD_134", "AND_137", "89"],
    ["AND_137", "STR_143", "91"],
    ["ADD_142", "STR_143", "94"],
    ["ADD_145", "LOD_146", "96"],
    ["LOD_146", "LSR_150", "97"],
    ["LSR_150", "AND_152", "99"],
    ["AND_152", "STR_158", "101"],
    ["ADD_157", "STR_158", "104"],
    ["ADD_160", "LOD_161", "106"],
    ["LOD_161", "LSR_165", "107"],
    ["LSR_165", "AND_167", "109"],
    ["AND_167", "STR_173", "111"],
    ["ADD_172", "STR_173", "114"],
    ["ADD_175", "LOD_176", "116"],
    ["LOD_176", "LSR_180", "117"],
    ["LSR_180", "AND_182", "119"],
    ["AND_182", "STR_188", "121"],
    ["ADD_187", "STR_188", "124"],
    ["ADD_190", "LOD_191", "126"],
    ["LOD_191", "AND_194", "127"],
    ["AND_194", "STR_200", "129"],
    ["ADD_199", "STR_200", "132"],
    ["ADD_202", "LOD_203", "134"],
    ["LOD_203", "LSR_207", "135"],
    ["LSR_207", "AND_209", "137"],
    ["AND_209", "STR_215", "139"],
    ["ADD_214", "STR_215", "142"],
    ["ADD_217", "LOD_218", "144"],
    ["LOD_218", "LSR_222", "145"],
    ["LSR_222", "AND_224", "147"],
    ["AND_224", "STR_230", "149"],
    ["ADD_229", "STR_230", "152"],
    ["ADD_232", "LOD_233", "154"],
    ["LOD_233", "LSR_237", "155"],
    ["LSR_237", "AND_239", "157"],
    ["AND_239", "STR_245", "159"],
    ["ADD_244", "STR_245", "162"],
    ["ADD_250", "STR_251", "166"],
    ["ADD_256", "STR_257", "170"],
    ["AND_259", "STR_265", "172"],
    ["ADD_264", "STR_265", "175"],
    ["ASR_267", "AND_269", "177"],
    ["AND_269", "STR_275", "179"],
    ["ADD_274", "STR_275", "182"],
    ["ADD_277", "LOD_278", "184"],
    ["LOD_278", "BNE_282", "185"]
  ]
}
